dcraft/__init__.py
dcraft/domain/__init__.py
dcraft/domain/error/__init__.py
dcraft/domain/layer/__init__.py
dcraft/domain/layer/base.py
dcraft/domain/layer/raw.py
dcraft/domain/layer/refined.py
dcraft/domain/layer/trusted.py
dcraft/domain/loader/__init__.py
dcraft/domain/loader/metadata.py
dcraft/domain/loader/raw.py
dcraft/domain/loader/refined.py
dcraft/domain/loader/trusted.py
dcraft/domain/metadata/__init__.py
dcraft/domain/type/__init__.py
dcraft/domain/type/content.py
dcraft/domain/type/enum.py
dcraft/interface/__init__.py
dcraft/interface/data/__init__.py
dcraft/interface/data/base.py
dcraft/interface/data/gcs.py
dcraft/interface/data/local.py
dcraft/interface/data/minio.py
dcraft/interface/metadata/__init__.py
dcraft/interface/metadata/base.py
dcraft/interface/metadata/bq.py
dcraft/interface/metadata/local.py
dcraft/interface/metadata/mongo.py
dcraft/interface/metadata/setting.py
dcraft-0.5.2.dist-info/LICENSE
dcraft-0.5.2.dist-info/METADATA
dcraft-0.5.2.dist-info/WHEEL
dcraft-0.5.2.dist-info/top_level.txt
dcraft-0.5.2.dist-info/RECORD
