Metadata-Version: 2.1
Name: dcraft
Version: 0.5.2
Author: Shuhei Kishi
License-File: LICENSE
Requires-Dist: pandas
Requires-Dist: pyarrow
Provides-Extra: gcp
Requires-Dist: google-cloud-storage >=2.6.0 ; extra == 'gcp'
Requires-Dist: google-cloud-bigquery ; extra == 'gcp'
Requires-Dist: pyarrow ; extra == 'gcp'
Provides-Extra: minio
Requires-Dist: minio ; extra == 'minio'
Provides-Extra: mongo
Requires-Dist: pymongo ; extra == 'mongo'
Provides-Extra: test
Requires-Dist: pytest ; extra == 'test'
